autotransformers/__init__.py
autotransformers/augmentation/TextAugmenterPipeline.py
autotransformers/augmentation/__init__.py
autotransformers/augmentation/augmenter_config.py
autotransformers/autotrainer.py
autotransformers/ckpt_cleaner.py
autotransformers/dataset_config.py
autotransformers/default_param_spaces.py
autotransformers/hfdatasets_manager.py
autotransformers/hftransformers_manager.py
autotransformers/llm_templates.py
autotransformers/metrics.py
autotransformers/metrics_plotter.py
autotransformers/model_config.py
autotransformers/results_getter.py
autotransformers/skip_mix.py
autotransformers/tokenization_functions.py
autotransformers/utils.py
autotransformers-0.0.13.dist-info/LICENSE
autotransformers-0.0.13.dist-info/METADATA
autotransformers-0.0.13.dist-info/WHEEL
autotransformers-0.0.13.dist-info/RECORD
