Metadata-Version: 2.3
Name: autotransformers
Version: 0.0.13
Summary: a Python package for automatic training and benchmarking of Language Models.
License: CC BY-NC-SA 4.0
Keywords: large-language-models,language-models,natural-language-processing,nlp,transformers,hyperparameter-tuning,automatic-training
Author: LenguajeNatural.AI
Author-email: avaca@lenguajenatural.ai
Requires-Python: >=3.9.13,<4.0.0
Classifier: Development Status :: 5 - Production/Stable
Classifier: Intended Audience :: Science/Research
Classifier: License :: Other/Proprietary License
Classifier: Operating System :: OS Independent
Classifier: Programming Language :: Python
Classifier: Programming Language :: Python :: 3
Classifier: Programming Language :: Python :: 3.10
Classifier: Programming Language :: Python :: 3.11
Classifier: Programming Language :: Python :: 3.12
Classifier: Programming Language :: Python :: 3.13
Classifier: Programming Language :: Python :: 3.9
Classifier: Topic :: Scientific/Engineering
Requires-Dist: accelerate (>=0.27.2,<0.28.0)
Requires-Dist: apscheduler (>=3.6.3,<4.0.0)
Requires-Dist: bitsandbytes (>=0.42.0,<0.43.0)
Requires-Dist: datasets (>=2.17.1,<3.0.0)
Requires-Dist: einops (>=0.6.1,<0.7.0)
Requires-Dist: evaluate (>=0.2.2,<0.3.0)
Requires-Dist: more-itertools (>=8.14.0,<9.0.0)
Requires-Dist: nlpaug (>=1.1.11,<2.0.0)
Requires-Dist: nltk (>=3.7,<4.0)
Requires-Dist: optuna (>=3.0.2,<4.0.0)
Requires-Dist: pandas (>=2.0.0,<2.3.0)
Requires-Dist: peft (>=0.8.2,<0.9.0)
Requires-Dist: polyfuzz (>=0.4.0,<0.5.0)
Requires-Dist: pytest (>=7.1.3,<8.0.0)
Requires-Dist: rouge_score (>=0.1.2,<0.2.0)
Requires-Dist: scikit-learn (>=1.0.2,<2.0.0)
Requires-Dist: scipy (>=1.11.0,<2.0.0)
Requires-Dist: seaborn (>=0.12.0,<0.13.0)
Requires-Dist: sentencepiece (>=0.1.97,<0.2.0)
Requires-Dist: seqeval (>=1.2.2,<2.0.0)
Requires-Dist: simpletransformers (>=0.61.10,<0.62.0)
Requires-Dist: tensorboard (>=2.10.1,<3.0.0)
Requires-Dist: tensorboardX (>=2.5.1,<3.0.0)
Requires-Dist: tqdm (>=4.64.1,<5.0.0)
Requires-Dist: transformers[torch] (>=4.38.2,<5.0.0)
Project-URL: Homepage, https://lenguajenatural.ai
Project-URL: Repository, https://github.com/lenguajenatural-ai/autotransformers
